basiclogger/__init__.py
basiclogger/logger.py
basiclogger-0.1.0.dist-info/licenses/LICENSE
basiclogger-0.1.0.dist-info/METADATA
basiclogger-0.1.0.dist-info/WHEEL
basiclogger-0.1.0.dist-info/top_level.txt
basiclogger-0.1.0.dist-info/RECORD
