Metadata-Version: 2.4
Name: basiclogger
Version: 0.1.0
Summary: A simple colorful logger package with custom levels and timing decorator
Home-page: https://github.com/vincentdeneuf/basiclogger
Author: vincentdeneuf
Author-email: 0189vn@gmail.com
License: MIT
Classifier: Programming Language :: Python :: 3
Classifier: License :: OSI Approved :: MIT License
Classifier: Operating System :: OS Independent
Requires-Python: >=3.6
License-File: LICENSE
Dynamic: license-file
